mypy_boto3_macie/__init__.py
mypy_boto3_macie/__init__.pyi
mypy_boto3_macie/__main__.py
mypy_boto3_macie/client.py
mypy_boto3_macie/client.pyi
mypy_boto3_macie/literals.py
mypy_boto3_macie/literals.pyi
mypy_boto3_macie/paginator.py
mypy_boto3_macie/paginator.pyi
mypy_boto3_macie/py.typed
mypy_boto3_macie/type_defs.py
mypy_boto3_macie/type_defs.pyi
mypy_boto3_macie/version.py
mypy_boto3_macie-1.29.0.dist-info/LICENSE
mypy_boto3_macie-1.29.0.dist-info/METADATA
mypy_boto3_macie-1.29.0.dist-info/WHEEL
mypy_boto3_macie-1.29.0.dist-info/top_level.txt
mypy_boto3_macie-1.29.0.dist-info/RECORD
