Metadata-Version: 2.1
Name: mypy-boto3-macie
Version: 1.29.0
Summary: Type annotations for boto3.Macie 1.29.0 service generated with mypy-boto3-builder 7.20.3
Home-page: https://github.com/youtype/mypy_boto3_builder
Author: Vlad Emelianov
Author-email: vlad.emelianov.nz@gmail.com
License: MIT License
Project-URL: Documentation, https://youtype.github.io/boto3_stubs_docs/mypy_boto3_macie/
Project-URL: Source, https://github.com/youtype/mypy_boto3_builder
Project-URL: Tracker, https://github.com/youtype/mypy_boto3_builder/issues
Keywords: boto3 macie type-annotations botocore mypy typeshed autocomplete
Classifier: Development Status :: 5 - Production/Stable
Classifier: Intended Audience :: Developers
Classifier: Environment :: Console
Classifier: License :: OSI Approved :: MIT License
Classifier: Natural Language :: English
Classifier: Operating System :: OS Independent
Classifier: Programming Language :: Python :: 3
Classifier: Programming Language :: Python :: 3.7
Classifier: Programming Language :: Python :: 3.8
Classifier: Programming Language :: Python :: 3.9
Classifier: Programming Language :: Python :: 3.10
Classifier: Programming Language :: Python :: 3.11
Classifier: Programming Language :: Python :: 3.12
Classifier: Programming Language :: Python :: 3.13
Classifier: Programming Language :: Python :: 3 :: Only
Classifier: Programming Language :: Python :: Implementation :: CPython
Classifier: Typing :: Typed
Requires-Python: >=3.7
License-File: LICENSE
Requires-Dist: typing-extensions >=4.1.0 ; python_version < "3.12"
